plotto/__init__.py
plotto/datasets/load_data.py
plotto/datasets/params.csv
plotto/marks/__init__.py
plotto/marks/mark_plot.py
plotto/marks/utility.py
plotto/plotto.py
plotto/templates.py
plotto/tests/__init__.py
plotto/tests/test_mark_plot.py
plotto-0.1.3.dist-info/LICENSE.md
plotto-0.1.3.dist-info/WHEEL
plotto-0.1.3.dist-info/METADATA
plotto-0.1.3.dist-info/RECORD
